torchsurv/__init__.py
torchsurv/loss/__init__.py
torchsurv/loss/cox.py
torchsurv/loss/momentum.py
torchsurv/loss/survival.py
torchsurv/loss/weibull.py
torchsurv/metrics/__init__.py
torchsurv/metrics/auc.py
torchsurv/metrics/brier_score.py
torchsurv/metrics/cindex.py
torchsurv/stats/__init__.py
torchsurv/stats/ipcw.py
torchsurv/stats/kaplan_meier.py
torchsurv/tools/validate_data.py
torchsurv-0.1.6.dist-info/METADATA
torchsurv-0.1.6.dist-info/WHEEL
torchsurv-0.1.6.dist-info/licenses/LICENSE
torchsurv-0.1.6.dist-info/RECORD
