Metadata-Version: 2.4
Name: torchsurv
Version: 0.1.6
Summary: Deep survival analysis made easy with pytorch
Project-URL: Homepage, https://github.com/Novartis/torchsurv
Project-URL: Repository, https://github.com/Novartis/torchsurv
Project-URL: Documentation, https://opensource.nibr.com/torchsurv/
Project-URL: IssueTracker, https://github.com/Novartis/torchsurv/issues
Project-URL: Changelog, https://opensource.nibr.com/torchsurv/CHANGELOG.html
Author-email: Thibaud Coroller <thibaud.coroller@novartis.com>, Melodie Monod <monod.melodie@gmail.com>, Peter Krusche <peter.krusche@novartis.com>, Qian Cao <qian.cao@fda.hhs.com>
License: The MIT License (MIT)
License-File: LICENSE
Keywords: censored data,deep learning,machine learning,neural networks,pytorch,survival analysis,survival models
Classifier: Development Status :: 5 - Production/Stable
Classifier: Intended Audience :: Developers
Classifier: License :: OSI Approved :: MIT License
Classifier: Programming Language :: Python :: 3
Classifier: Programming Language :: Python :: 3.8
Classifier: Programming Language :: Python :: 3.9
Classifier: Programming Language :: Python :: 3.10
Classifier: Programming Language :: Python :: 3.11
Requires-Python: >=3.8
Requires-Dist: numpy
Requires-Dist: scipy
Requires-Dist: torch
Requires-Dist: torchmetrics
Provides-Extra: dev
Requires-Dist: hypothesis>=6.0; extra == 'dev'
Requires-Dist: mypy>=1.7; extra == 'dev'
Requires-Dist: pre-commit>=3.0; extra == 'dev'
Requires-Dist: pytest-cov>=4.0; extra == 'dev'
Requires-Dist: pytest-xdist>=3.0; extra == 'dev'
Requires-Dist: pytest>=7.0; extra == 'dev'
Requires-Dist: ruff>=0.1.0; extra == 'dev'
Provides-Extra: docs
Requires-Dist: jupyter-book; extra == 'docs'
Requires-Dist: numpydoc; extra == 'docs'
Requires-Dist: sphinx-autoapi; extra == 'docs'
Requires-Dist: sphinx-rtd-theme; extra == 'docs'
Requires-Dist: sphinx>=7.0; extra == 'docs'
